neural_state_manipulator/__init__.py
neural_state_manipulator/manipulator.py
neural_state_manipulator/util.py
neural_state_manipulator/utils.py
neural_state_manipulator-0.1.0.dist-info/licenses/LICENSE.md
neural_state_manipulator-0.1.0.dist-info/METADATA
neural_state_manipulator-0.1.0.dist-info/WHEEL
neural_state_manipulator-0.1.0.dist-info/top_level.txt
neural_state_manipulator-0.1.0.dist-info/RECORD
