Metadata-Version: 2.4
Name: neural-state-manipulator
Version: 0.1.0
Summary: A tool for manipulating the internal neural activations of language models
Home-page: https://github.com/harishsg993010/neural-state-manipulator
Author: Harish Santhana Lakshmi Ganesan
Author-email: Harish Santhana Lakshmi Ganesan <harishsg99@gmail.com>
License: MIT
Project-URL: Homepage, https://github.com/harishsg993010/neural-state-manipulator
Project-URL: Bug Tracker, https://github.com/harishsg993010/neural-state-manipulator/issues
Keywords: machine learning,natural language processing,neural networks,transformers
Classifier: Programming Language :: Python :: 3
Classifier: License :: OSI Approved :: MIT License
Classifier: Operating System :: OS Independent
Classifier: Topic :: Scientific/Engineering :: Artificial Intelligence
Requires-Python: >=3.8
License-File: LICENSE.md
Requires-Dist: torch>=2.6.0
Requires-Dist: transformers>=4.50.3
Requires-Dist: numpy>=2.0.2
Requires-Dist: bitsandbytes>=0.45.4
Dynamic: author
Dynamic: home-page
Dynamic: license-file
Dynamic: requires-python
